{
	"format_version": "1.12.0",
	"minecraft:geometry": [
		{
			"description": {
				"identifier": "geometry.plush_gasgolder",
				"texture_width": 32,
				"texture_height": 32,
				"visible_bounds_width": 2,
				"visible_bounds_height": 2.5,
				"visible_bounds_offset": [0, 0.75, 0]
			},
			"bones": [
				{
					"name": "All",
					"pivot": [0, 0, 0]
				},
				{
					"name": "head",
					"parent": "All",
					"pivot": [0, 7.34151, -0.925],
					"cubes": [
						{"origin": [-2, 5, -3], "size": [4, 3, 5], "uv": [0, 0]},
						{"origin": [-1, 5, -5], "size": [2, 2, 2], "uv": [22, 18]},
						{"origin": [1, 7, 0], "size": [2, 2, 1], "pivot": [2.1, 7.5, 0.5], "rotation": [0, -90, 90], "uv": [6, 26]},
						{"origin": [-3, 7, 0], "size": [2, 2, 1], "pivot": [-2.1, 7.5, 0.5], "rotation": [0, 90, -90], "uv": [22, 26]}
					]
				},
				{
					"name": "hat",
					"parent": "head",
					"pivot": [-2.14605, 7.17825, 0.5],
					"cubes": [
						{"origin": [-2, 8.1, -2.5], "size": [5, 0, 5], "uv": [0, 8]},
						{"origin": [-3.64355, 8.8664, -2.5], "size": [2, 0, 5], "pivot": [-2.64355, 8.8664, 0], "rotation": [0, 0, 50], "uv": [14, 13]},
						{"origin": [-1.4, 8.1, -1.5], "size": [3, 1, 3], "uv": [18, 0]},
						{"origin": [-1.4, 8.1, -0.5], "size": [0, 5, 4], "pivot": [-1.4, 8.1, 0], "rotation": [0, 0, -10], "uv": [14, 18]}
					]
				},
				{
					"name": "legs",
					"parent": "All",
					"pivot": [3, 0, -5],
					"cubes": [
						{"origin": [-3.5, 0, -3], "size": [2, 2, 2], "uv": [20, 9]},
						{"origin": [1.5, 0, -3], "size": [2, 2, 2], "uv": [0, 21]}
					]
				},
				{
					"name": "Body",
					"parent": "All",
					"pivot": [0, 0, 0],
					"cubes": [
						{"origin": [-2, 0, -1], "size": [4, 5, 3], "uv": [0, 13]}
					]
				},
				{
					"name": "backpack",
					"parent": "Body",
					"pivot": [0, 0, 0],
					"cubes": [
						{"origin": [-2, 1, 2], "size": [4, 4, 1], "uv": [20, 4]},
						{"origin": [-2.75, 1, 1.75], "size": [1, 3, 1], "uv": [28, 9]},
						{"origin": [1.75, 1, 1.75], "size": [1, 3, 1], "uv": [28, 13]}
					]
				},
				{
					"name": "chawisaw",
					"parent": "backpack",
					"pivot": [0, 0, 0],
					"cubes": [
						{"origin": [2.75, 5.1, 3], "size": [1, 2, 1], "pivot": [3.25, 6.1, 3.5], "rotation": [0, 0, 70], "uv": [6, 29]},
						{"origin": [0.05, 2.2, 3], "size": [1, 3, 1], "pivot": [0.55, 4.2, 3.5], "rotation": [0, 0, 72], "uv": [28, 26]},
						{"origin": [-4.1, 1.65, 3.5], "size": [4, 4, 0], "pivot": [-1.6, 3.65, 4], "rotation": [0, 0, -45], "uv": [22, 22]},
						{"origin": [1.4, 4.15, 3], "size": [1, 2, 1], "pivot": [1.9, 5.15, 3.5], "rotation": [0, 0, 40], "uv": [20, 29]},
						{"origin": [-2.5, 3.75, 3.4], "size": [1, 1, 1], "pivot": [-2.5, 3.75, 8.4], "rotation": [0, 0, 72], "uv": [0, 0]},
						{"origin": [-2.5, 3.75, 2.6], "size": [1, 1, 1], "pivot": [-2.5, 3.75, 7.6], "rotation": [0, 0, 72], "uv": [0, 0]}
					]
				},
				{
					"name": "hands",
					"parent": "All",
					"pivot": [0, 0, 0],
					"cubes": [
						{"origin": [-3, 2, -0.5], "size": [1, 3, 2], "pivot": [-2, 5, 0.5], "rotation": [0, 0, 2.5], "uv": [8, 21]},
						{"origin": [2, 2, -0.5], "size": [1, 3, 2], "pivot": [2, 5, 0.5], "rotation": [0, 0, -2.5], "uv": [0, 25]}
					]
				},
				{
					"name": "claws",
					"parent": "hands",
					"pivot": [0, 0, 0],
					"cubes": [
						{"origin": [-3.2, 1, -0.5], "size": [0, 2, 2], "pivot": [-3.2, 2, 0.5], "rotation": [0, 0, 2.5], "uv": [12, 27]},
						{"origin": [3.2, 1, -0.5], "size": [0, 2, 2], "pivot": [3.2, 2, 0.5], "rotation": [0, 0, -2.5], "uv": [16, 27]}
					]
				},
				{
					"name": "head2",
					"parent": "All",
					"pivot": [0, 7.34151, -0.925]
				},
				{
					"name": "hat2",
					"parent": "head2",
					"pivot": [2.14605, 7.97825, 0.5]
				}
			]
		}
	]
}