{
	"format_version": "1.19.0",
	"animation_controllers": {
		"controller.animation.gabz.basic": {
			"initial_state": "idle",
			"states": {
				"idle": {
					"animations": [
						"basic",
						"blink",
						{"attack": "variable.attack_time > 0"}
					],
					"transitions": [
						{"walking": "q.ground_speed > 1.0"}
					],
					"blend_transition": 0.2
				},
				"walking": {
					"animations": [
						"walk",
						"basic",
						{"attack": "variable.attack_time > 0"}
					],
					"transitions": [
						{"idle": "q.ground_speed < 0.5"}
					],
					"blend_transition": 0.2
				}
			}
		}
	}
}