{
	"format_version": "1.16.0",
	"minecraft:entity": {
		"description": {
			"identifier": "arx:blocking_invisible_shield",
			"is_spawnable": true,
			"is_summonable": true
		},
		"components": {
			"minecraft:type_family": {
				"family": [
					"logical"
				]
			},
			"minecraft:health": {
				"value": 999999
			},
			"minecraft:timer": {
				"looping": false,
				"time": 1.0,
				"time_down_event": {
					"event": "arx:suicide"
				}
			},
			"minecraft:knockback_resistance": {
				"value": 1.0
			},
			"minecraft:pushable": {
				"is_pushable": false,
				"is_pushable_by_piston": false
			},
			"minecraft:damage_sensor": {
				"triggers": [
					{
						"cause": "all",
						"deals_damage": false,
						"on_damage": {
							"event": "arx:on_hit"
						}
					}
				]
			},
			"minecraft:collision_box": {
				"width": 1.2,
				"height": 2.0
			}
		},
		"component_groups": {
			"arx:suicide": {
				"minecraft:instant_despawn": {}
			},
			"arx:fast_expire": {
				"minecraft:timer": {
					"looping": false,
					"time": 0.1,
					"time_down_event": {
						"event": "arx:suicide"
					}
				}
			}
		},
		"events": {
			"arx:suicide": {
				"add": {
					"component_groups": [
						"arx:suicide"
					]
				}
			},
			"arx:on_hit": {
				"queue_command": {
					"command": [
						"playsound on_block @a ~ ~ ~",
						"execute at @p positioned ~ ~1.0 ~ positioned ^ ^ ^0.5 run particle arx:blocking_sparks"
					]
				}
			}
		}
	}
}